sopel_modules.chanlogs-0.2.3.post0-py3.12-nspkg.pth
sopel_modules/chanlogs/__init__.py
sopel_modules.chanlogs-0.2.3.post0.dist-info/METADATA
sopel_modules.chanlogs-0.2.3.post0.dist-info/WHEEL
sopel_modules.chanlogs-0.2.3.post0.dist-info/namespace_packages.txt
sopel_modules.chanlogs-0.2.3.post0.dist-info/top_level.txt
sopel_modules.chanlogs-0.2.3.post0.dist-info/RECORD
