Metadata-Version: 2.1
Name: sopel_modules.chanlogs
Version: 0.2.3.post0
Summary: A channel logging plugin for Sopel (replaced)
Home-page: https://github.com/sopel-irc/sopel-chanlogs
Author: dgw
Author-email: dgw@technobabbl.es
Requires-Dist: sopel <8,>=7.0
